{
  "date": "2026-07-05",
  "puzzle_num": 1586,
  "word": "arranger",
  "first_letter": "A",
  "word_length": 8,
  "definition": "Mettre dans un certain ordre, dans l’ordre convenable.",
  "hints": {
    "level1": [
      {
        "word": "excité",
        "percentile": 200,
        "definition": ""
      },
      {
        "word": "écouter",
        "percentile": 267,
        "definition": "L’ouïe est la capacité de percevoir des sons et constitue l’un des cinq sens généralement reconnus."
      },
      {
        "word": "autant",
        "percentile": 334,
        "definition": ""
      }
    ],
    "level2": [
      {
        "word": "self-control",
        "percentile": 500,
        "definition": "Self control est une expression anglaise désignant le contrôle de soi ou la maîtrise de soi."
      },
      {
        "word": "temps",
        "percentile": 567,
        "definition": "Le temps est une notion qui rend compte du changement dans le monde."
      },
      {
        "word": "gugusse",
        "percentile": 634,
        "definition": "Gugusse est une pièce de théâtre de Marcel Achard créée au théâtre de la Michodière le 13 septembre 1968."
      }
    ],
    "level3": [
      {
        "word": "forcer",
        "percentile": 800,
        "definition": ""
      },
      {
        "word": "rajouter",
        "percentile": 850,
        "definition": ""
      },
      {
        "word": "fatiguer",
        "percentile": 900,
        "definition": ""
      }
    ]
  },
  "tried_count": 131,
  "generated_at": "2026-07-04T22:16:33.613030+00:00"
}