{
  "date": "2026-02-02",
  "puzzle_num": 1360,
  "word": "Écritures du japonais",
  "title_slug": "Écritures_du_japonais",
  "title_display": "Écritures du japonais",
  "wikipedia_url": "https://fr.wikipedia.org/wiki/Écritures_du_japonais",
  "hints": {
    "level1": [
      "3 mots · 19 lettres",
      "Premières lettres : É · D · J"
    ],
    "level2": [
      "Catégories non disponibles"
    ],
    "level3": [
      "Extrait non disponible"
    ]
  },
  "extract": "",
  "categories": [],
  "generated_at": "2026-04-28T22:16:25.522042+00:00"
}